alfred/__init__.py
alfred/base/__init__.py
alfred/base/config.py
alfred/base/constants.py
alfred/base/exceptions.py
alfred/base/typed.py
alfred/exceptions/__init__.py
alfred/http/__init__.py
alfred/http/http_client.py
alfred/http/typed.py
alfred/realtime/__init__.py
alfred/rest/__init__.py
alfred/rest/data_points/__init__.py
alfred/rest/data_points/base.py
alfred/rest/data_points/v1.py
alfred/rest/files/__init__.py
alfred/rest/files/base.py
alfred/rest/files/typed.py
alfred/rest/files/v1.py
alfred/rest/jobs/__init__.py
alfred/rest/jobs/base.py
alfred/rest/jobs/typed.py
alfred/rest/jobs/v1.py
alfred/rest/sessions/__init__.py
alfred/rest/sessions/base.py
alfred/rest/sessions/v1.py
alfred/typings/__init__.py
alfred/typings/misc.py
alfred/utils/__init__.py
alfred/utils/logging.py
alfred_python-0.6.3.dist-info/LICENSE
alfred_python-0.6.3.dist-info/METADATA
alfred_python-0.6.3.dist-info/WHEEL
alfred_python-0.6.3.dist-info/top_level.txt
alfred_python-0.6.3.dist-info/RECORD
