Metadata-Version: 2.1
Name: alfred-python
Version: 0.6.3
Summary: Python library designed to simplify and streamline interactions with the Alfred API
Author-email: Tagshelf LLC <support@tagshelf.com>
License: Copyright (c) 2018 The Python Packaging Authority
Project-URL: homepage, https://github.com/tagshelfsrl/alfred-python
Classifier: Programming Language :: Python :: 3
Classifier: License :: OSI Approved :: MIT License
Classifier: Operating System :: OS Independent
Requires-Python: >=3.8
License-File: LICENSE
Requires-Dist: pydantic >=2.0
Requires-Dist: pydantic-settings >=2.0
Requires-Dist: requests >=2.30
Requires-Dist: python-socketio >=5.11
Requires-Dist: websocket-client >=1.8
Requires-Dist: python-magic ==0.4.27 ; platform_system != "Windows"
Requires-Dist: python-magic-bin ==0.4.14 ; platform_system == "Windows"
